notetiktok/__init__.py
notetiktok/data/__init__.py
notetiktok/data/base.py
notetiktok/data/data.py
notectiktok-0.0.5.dist-info/METADATA
notectiktok-0.0.5.dist-info/WHEEL
notectiktok-0.0.5.dist-info/entry_points.txt
notectiktok-0.0.5.dist-info/top_level.txt
notectiktok-0.0.5.dist-info/RECORD
