Metadata-Version: 2.1
Name: notectiktok
Version: 0.0.5
Summary: notectiktok
Home-page: https://github.com/1007530194
Author: niult
Author-email: 1007530194@qq.com
License: UNKNOWN
Platform: UNKNOWN
Requires-Dist: tqdm
Requires-Dist: supervisor
